csp/__init__.py
csp/apps.py
csp/checks.py
csp/constants.py
csp/context_processors.py
csp/decorators.py
csp/exceptions.py
csp/middleware.py
csp/models.py
csp/py.typed
csp/utils.py
csp/contrib/__init__.py
csp/contrib/rate_limiting.py
csp/extensions/__init__.py
csp/migrations/0001_initial.py
csp/migrations/0002_alter_contentsecuritypolicysettings_options.py
csp/migrations/0003_alter_contentsecuritypolicysettings_csp_script_src.py
csp/migrations/__init__.py
csp/templatetags/__init__.py
csp/templatetags/csp.py
csp/tests/__init__.py
csp/tests/environment.py
csp/tests/settings.py
csp/tests/test_checks.py
csp/tests/test_constants.py
csp/tests/test_context_processors.py
csp/tests/test_contrib.py
csp/tests/test_decorators.py
csp/tests/test_jinja_extension.py
csp/tests/test_middleware.py
csp/tests/test_templatetags.py
csp/tests/test_utils.py
csp/tests/test_utils_db.py
csp/tests/utils.py
wagtail_csp-4.0.dist-info/licenses/LICENSE
wagtail_csp-4.0.dist-info/METADATA
wagtail_csp-4.0.dist-info/WHEEL
wagtail_csp-4.0.dist-info/top_level.txt
wagtail_csp-4.0.dist-info/RECORD
